DronePy/Controller.py
DronePy/__init__.py
DronePy/Devices/Device.py
DronePy/Devices/__init__.py
DronePy/Devices/limeSDR.py
DronePy/Models/DX-2.py
DronePy/Models/DX2.py
DronePy/Models/DroneModel.py
DronePy/Models/__init__.py
DronePy/Models/base.py
DronePy/Transcievers/__init__.py
DronePy/Transcievers/base.py
DronePy/Transcievers/limeSDR.py
Models/DX-2.py
Models/__init__.py
Models/base.py
Transcievers/__init__.py
Transcievers/base.py
Transcievers/limeSDR.py
DronePy-0.0.3.dist-info/LICENSE
DronePy-0.0.3.dist-info/METADATA
DronePy-0.0.3.dist-info/WHEEL
DronePy-0.0.3.dist-info/top_level.txt
DronePy-0.0.3.dist-info/RECORD
