Metadata-Version: 2.1
Name: DronePy
Version: 0.0.3
Summary: Open Source Drone Interface Library
Home-page: https://github.com/deleomike/DronePy
Author: Michael DeLeo
Author-email: michaeldeleo31@yahoo.com
License: UNKNOWN
Platform: UNKNOWN
Classifier: Programming Language :: Python :: 3
Classifier: License :: OSI Approved :: MIT License
Classifier: Operating System :: OS Independent
Classifier: Development Status :: 1 - Planning
Classifier: Natural Language :: English
Classifier: Programming Language :: Python :: Implementation
Classifier: Topic :: Communications
Classifier: Topic :: Scientific/Engineering
Classifier: Topic :: Scientific/Engineering :: Artificial Intelligence
Classifier: Topic :: Software Development :: Libraries :: Python Modules
Requires-Python: >=3.6
Requires-Dist: numpy
Requires-Dist: matplotlib
Requires-Dist: pyserial
